genelastic/__init__.py
genelastic/api/.env
genelastic/api/__init__.py
genelastic/api/cli_start_api.py
genelastic/api/errors.py
genelastic/api/extends/__init__.py
genelastic/api/extends/example.py
genelastic/api/extends/example.yml
genelastic/api/routes.py
genelastic/api/server.py
genelastic/api/settings.py
genelastic/api/specification.yml
genelastic/common/__init__.py
genelastic/common/cli.py
genelastic/common/elastic.py
genelastic/common/exceptions.py
genelastic/common/server.py
genelastic/common/types.py
genelastic/import_data/__init__.py
genelastic/import_data/checker.py
genelastic/import_data/checker_observer.py
genelastic/import_data/cli/__init__.py
genelastic/import_data/cli/cli_check.py
genelastic/import_data/cli/gen_data.py
genelastic/import_data/cli/import_data.py
genelastic/import_data/cli/info.py
genelastic/import_data/cli/integrity.py
genelastic/import_data/cli/validate.py
genelastic/import_data/collect.py
genelastic/import_data/constants.py
genelastic/import_data/import_bundle.py
genelastic/import_data/import_bundle_factory.py
genelastic/import_data/importers/__init__.py
genelastic/import_data/importers/importer_base.py
genelastic/import_data/importers/importer_factory.py
genelastic/import_data/importers/importer_types.py
genelastic/import_data/logger.py
genelastic/import_data/models/__init__.py
genelastic/import_data/models/analyses.py
genelastic/import_data/models/analysis.py
genelastic/import_data/models/data_file.py
genelastic/import_data/models/process.py
genelastic/import_data/models/processes.py
genelastic/import_data/models/tags.py
genelastic/import_data/models/unique_list.py
genelastic/import_data/models/validate.py
genelastic/import_data/patterns.py
genelastic/import_data/random_bundle.py
genelastic/import_data/resolve.py
genelastic/ui/.env
genelastic/ui/__init__.py
genelastic/ui/cli_start_ui.py
genelastic/ui/routes.py
genelastic/ui/server.py
genelastic/ui/settings.py
genelastic/ui/static/cea-cnrgh.ico
genelastic/ui/static/cea.ico
genelastic-0.9.0.dist-info/licenses/LICENSE
genelastic-0.9.0.dist-info/WHEEL
genelastic-0.9.0.dist-info/entry_points.txt
genelastic-0.9.0.dist-info/METADATA
genelastic-0.9.0.dist-info/RECORD
