Metadata-Version: 2.4
Name: genelastic
Version: 0.9.0
Summary: Generate and store genetic data into an Elasticsearch database.
Keywords: CNRGH,genelastic,generation,storage,elasticsearch,database
Author: CNRGH, Pierrick ROGER, Maxime BLANCHON
Author-email: Pierrick ROGER <pierrick.roger@cnrgh.fr>, Maxime BLANCHON <maxime.blanchon@cnrgh.fr>
License-Expression: CECILL-2.1
License-File: LICENSE
Classifier: Development Status :: 3 - Alpha
Classifier: Intended Audience :: Science/Research
Classifier: Programming Language :: Python :: 3.11
Requires-Dist: elasticsearch>=8.18.1,<8.19.0
Requires-Dist: pyvcf3>=1.0.3,<2.0.0
Requires-Dist: schema>=0.7.7,<0.8.0
Requires-Dist: pyyaml>=6.0.2,<7.0.0
Requires-Dist: biophony>=1.3.0,<1.4.0
Requires-Dist: colorlog>=6.9.0,<7.0.0
Requires-Dist: tqdm>=4.67.1,<5.0.0
Requires-Dist: flask>=3.1.0,<4.0.0 ; extra == 'api'
Requires-Dist: environs>=14.1.1,<15.0.0 ; extra == 'api'
Requires-Dist: connexion[flask,swagger-ui,uvicorn]>=3.2.0,<4.0.0 ; extra == 'api'
Requires-Dist: gunicorn>=23.0.0,<24.0.0 ; extra == 'api'
Requires-Dist: flask>=3.1.0,<4.0.0 ; extra == 'ui'
Requires-Dist: requests>=2.32.3,<3.0.0 ; extra == 'ui'
Requires-Dist: environs>=14.1.1,<15.0.0 ; extra == 'ui'
Requires-Dist: uvicorn>=0.34.0,<0.35.0 ; extra == 'ui'
Requires-Dist: asgiref>=3.8.1,<4.0.0 ; extra == 'ui'
Requires-Dist: gunicorn>=23.0.0,<24.0.0 ; extra == 'ui'
Requires-Python: >=3.11
Provides-Extra: api
Provides-Extra: ui
